pmf_searchbox/__init__.py
pmf_searchbox/searchbox.py
pmf_searchbox-0.0.3.dist-info/LICENSE
pmf_searchbox-0.0.3.dist-info/METADATA
pmf_searchbox-0.0.3.dist-info/WHEEL
pmf_searchbox-0.0.3.dist-info/top_level.txt
pmf_searchbox-0.0.3.dist-info/RECORD
